pyxo/__init__.py
pyxo/__main__.py
pyxo/controler/__init__.py
pyxo/controler/engin.py
pyxo/models/__init__.py
pyxo/models/board.py
pyxo/models/player.py
pyxo/utils.py
pyxo/views/__init__.py
pyxo/views/addplayer.py
pyxo/views/playagain.py
pyxo/views/playing.py
pyxo/views/showiner.py
pyxo/views/start.py
pyxo/views/view.py
pyxo-1.2.2.dist-info/LICENSE
pyxo-1.2.2.dist-info/METADATA
pyxo-1.2.2.dist-info/WHEEL
pyxo-1.2.2.dist-info/entry_points.txt
pyxo-1.2.2.dist-info/RECORD
