Metadata-Version: 2.1
Name: pyxo
Version: 1.2.2
Summary: An easy way to create XO game with python.
Home-page: https://github.com/ouhammmourachid/pyxo
License: MIT
Author: ouhammmourachid
Author-email: rachidouhammou21@gmail.com
Requires-Python: >=3.10,<4.0
Classifier: License :: OSI Approved :: MIT License
Classifier: Programming Language :: Python :: 3
Classifier: Programming Language :: Python :: 3.10
Classifier: Programming Language :: Python :: 3.11
Classifier: Programming Language :: Python :: 3.12
Project-URL: Repository, https://github.com/ouhammmourachid/pyxo
